Metadata-Version: 2.1
Name: django-crontab-agent
Version: 0.1.7
Summary: Agent for django-crontab-manager. Installed the agent on the target server. The agent will sync  settings from the manager and update the crontab file every minutes. Note: It is an agent implementation of django-crontab-manager server.
Home-page: UNKNOWN
Author: zencore
Author-email: dobetter@zencore.cn
License: MIT
Keywords: django extensions
Platform: UNKNOWN
Classifier: Development Status :: 5 - Production/Stable
Classifier: Intended Audience :: Developers
Classifier: Topic :: Software Development :: Libraries :: Python Modules
Classifier: License :: OSI Approved :: MIT License
Classifier: Programming Language :: Python :: 3
Classifier: Programming Language :: Python :: 3 :: Only
